py_pip/__init__.py
py_pip-0.0.12.dist-info/METADATA
py_pip-0.0.12.dist-info/WHEEL
py_pip-0.0.12.dist-info/top_level.txt
py_pip-0.0.12.dist-info/RECORD
