Metadata-Version: 2.1
Name: py-pip
Version: 0.0.12
Summary: a PIP wrapper to install PyPI packages from inside Python
Author: Hannes
Project-URL: Homepage, https://github.com/hannesdelbeke/py-pip
Project-URL: Source, https://github.com/hannesdelbeke/py-pip
Keywords: manager,dcc,app
Classifier: Programming Language :: Python :: 3.7
Requires-Python: >=3.4
Requires-Dist: importlib-metadata ; python_version < "3.7"
